doubly_py_linked_list/__init__.py
doubly_py_linked_list/doubly_linked_list.py
doubly_py_linked_list-1.1.2.dist-info/LICENSE
doubly_py_linked_list-1.1.2.dist-info/METADATA
doubly_py_linked_list-1.1.2.dist-info/WHEEL
doubly_py_linked_list-1.1.2.dist-info/top_level.txt
doubly_py_linked_list-1.1.2.dist-info/RECORD
