Metadata-Version: 2.1
Name: doubly_py_linked_list
Version: 1.1.2
Summary: Doubly linked list implementation in Python
Author-email: "Konstantin (k0nze) Lübeck" <admin@konze.org>
License: BSD 3-Clause License
Project-URL: Homepage, https://github.com/k0nze/doubly_py_linked_list
Keywords: data structures
Classifier: License :: OSI Approved :: BSD License
Classifier: Programming Language :: Python
Classifier: Programming Language :: Python :: 3
Requires-Python: >=3.8
License-File: LICENSE
Provides-Extra: dev
Requires-Dist: pre-commit ; extra == 'dev'
Requires-Dist: bumpver ; extra == 'dev'
